frenchlearning/__init__.py
frenchlearning/full_suite.py
frenchlearning/test_classes.py
frenchlearning/test_initializer.py
frenchlearning/test_manager.py
frenchlearning/test_quizzing.py
frenchlearning/memorization/__init__.py
frenchlearning/memorization/classes.py
frenchlearning/memorization/initializer.py
frenchlearning/quiz/__init__.py
frenchlearning/quiz/main.py
frenchlearning/quiz/manager.py
frenchlearning/quiz/quizzing.py
frenchlearning-0.1.2.dist-info/LICENSE.txt
frenchlearning-0.1.2.dist-info/METADATA
frenchlearning-0.1.2.dist-info/WHEEL
frenchlearning-0.1.2.dist-info/top_level.txt
frenchlearning-0.1.2.dist-info/RECORD
