Metadata-Version: 2.1
Name: frenchlearning
Version: 0.1.2
Summary: A Python package for learning French, including memorization and quizzing modules.
Home-page: https://github.com/tianyi-xia1/project-step-3.git
Author: Tianyi Xia, Litao Zheng
Author-email: kevinhsia6@gmail.com, zhenglitao0305@gmail.com
Classifier: Programming Language :: Python :: 3
Classifier: License :: OSI Approved :: MIT License
Classifier: Operating System :: OS Independent
Classifier: Topic :: Education
Requires-Python: >=3.9
License-File: LICENSE.txt
